snapshooter/__init__.py
snapshooter/cache_utils.py
snapshooter/cli.py
snapshooter/fsspec_utils.py
snapshooter/jsonl_utils.py
snapshooter/logging_utils.py
snapshooter/snapshooter.py
tests/__init__.py
tests/conftest.py
tests/test_fsspec_utils.py
tests/test_snapshooter_default_use_cases.py
snapshooter-1.0.19.dist-info/LICENSE
snapshooter-1.0.19.dist-info/METADATA
snapshooter-1.0.19.dist-info/WHEEL
snapshooter-1.0.19.dist-info/entry_points.txt
snapshooter-1.0.19.dist-info/top_level.txt
snapshooter-1.0.19.dist-info/RECORD
