Metadata-Version: 2.1
Name: snapshooter
Version: 1.0.19
Summary: Provides a set of utilities for comparing and backing up data on different filesystems
Home-page: https://github.com/jeromerg/snapshooter
Author: jeromerg
Author-email: jeromerg@gmx.net
Classifier: Programming Language :: Python :: 3
Classifier: License :: OSI Approved :: MIT License
Classifier: Operating System :: OS Independent
Requires-Python: >=3.10
License-File: LICENSE
Requires-Dist: fsspec
Requires-Dist: pandas
Requires-Dist: tabulate
Requires-Dist: typer[all]
Requires-Dist: colorlog
Requires-Dist: tzlocal
